customisedLogs.py
customisedLogs-2.0.3.dist-info/METADATA
customisedLogs-2.0.3.dist-info/WHEEL
customisedLogs-2.0.3.dist-info/top_level.txt
customisedLogs-2.0.3.dist-info/RECORD
