Metadata-Version: 2.2
Name: customisedLogs
Version: 2.0.3
Summary: A well maintained package to have coloured logs on the terminal. This would help isolate errors and success messages from each other by their colours.
Maintainer-email: Bhindi <bhaskarpanja93@gmail.com>, riyapuri0710 <riyapuri0710@gmail.com>
Project-URL: Homepage, https://github.com/BhaskarPanja93/customisedLogs
Keywords: log,logs,pretty,prettified,color,colored,coloured logs,colored terminal,logger,tailwind
Classifier: License :: OSI Approved :: MIT License
Classifier: Programming Language :: Python
Classifier: Programming Language :: Python :: 3
Requires-Python: >=3.6
Requires-Dist: colr
